mplchart/__init__.py
mplchart/chart.py
mplchart/colors.py
mplchart/formatter.py
mplchart/indicators.py
mplchart/layout.py
mplchart/library.py
mplchart/locator.py
mplchart/mapper.py
mplchart/model.py
mplchart/modifiers.py
mplchart/plotters.py
mplchart/primitives/__init__.py
mplchart/primitives/areaplot.py
mplchart/primitives/axes.py
mplchart/primitives/barplot.py
mplchart/primitives/candlesticks.py
mplchart/primitives/lineplot.py
mplchart/primitives/markers.py
mplchart/primitives/ohlc.py
mplchart/primitives/peaks.py
mplchart/primitives/price.py
mplchart/primitives/stripes.py
mplchart/primitives/volume.py
mplchart/primitives/zigzag.py
mplchart/samples/__init__.py
mplchart/samples/daily-prices.csv
mplchart/samples/hourly-prices.csv
mplchart/samples/minute-prices.csv
mplchart/utils.py
mplchart-0.0.24.dist-info/WHEEL
mplchart-0.0.24.dist-info/METADATA
mplchart-0.0.24.dist-info/RECORD
