Metadata-Version: 2.3
Name: mplchart
Version: 0.0.24
Summary: Classic Stock Charts in Python
Keywords: finance,charting,matplotlib,candlesticks
Author: Furechan
Author-email: Furechan <furechan@xsmail.com>
Classifier: Programming Language :: Python :: 3
Classifier: License :: OSI Approved :: MIT License
Classifier: Operating System :: OS Independent
Requires-Dist: matplotlib
Requires-Dist: numpy
Requires-Dist: pandas
Requires-Python: >=3.9
Project-URL: homepage, https://github.com/furechan/mplchart
